doxxie/__init__.py
doxxie/doxxie.py
doxxie/py.typed
doxxie-0.2.dist-info/LICENSE
doxxie-0.2.dist-info/METADATA
doxxie-0.2.dist-info/WHEEL
doxxie-0.2.dist-info/top_level.txt
doxxie-0.2.dist-info/RECORD
