Metadata-Version: 2.1
Name: doxxie
Version: 0.2
Summary: Uncover your mypy-typed library's true public API
Home-page: https://github.com/Kyle-Verhoog/doxxie
Author: Kyle Verhoog
Author-email: kyle@verhoog.ca
License: BSD 3
Platform: UNKNOWN
Classifier: Programming Language :: Python
Classifier: Programming Language :: Python :: 3.6
Classifier: Programming Language :: Python :: 3.7
Classifier: Programming Language :: Python :: 3.8
Classifier: Programming Language :: Python :: 3.9
Requires-Python: >=3.6
Requires-Dist: mypy
